pygluon/__init__.py
pygluon/reactors/__init__.py
pygluon/reactors/gluon_reactor.py
pygluon/reactors/gluon_z_reactor.py
pygluon/reactors/types.py
pygluon-1.0.0.dist-info/METADATA
pygluon-1.0.0.dist-info/WHEEL
pygluon-1.0.0.dist-info/RECORD
