Metadata-Version: 2.4
Name: pygluon
Version: 1.0.0
Summary: Gluon simulator library for python.
Project-URL: Homepage, https://stability.nexus
Author-email: Luca D'Angelo <ldgaetano@protonmail.com>
License-Expression: MIT
Classifier: Development Status :: 3 - Alpha
Classifier: Intended Audience :: Science/Research
Classifier: License :: OSI Approved :: MIT License
Classifier: Operating System :: OS Independent
Classifier: Programming Language :: Python :: 3
Requires-Python: >=3.10
